a_rename/__init__.py
a_rename/main.py
a_rename-0.1.0.dist-info/WHEEL
a_rename-0.1.0.dist-info/METADATA
a_rename-0.1.0.dist-info/RECORD
