Metadata-Version: 2.1
Name: a-rename
Version: 0.1.0
Summary: 
Author: Matheus Henrique
Author-email: matheus2hcosta@gmail.com
Requires-Python: >=3.11,<4.0
Classifier: Programming Language :: Python :: 3
Classifier: Programming Language :: Python :: 3.11
Requires-Dist: debugpy (>=1.6.6,<2.0.0)
